flet_timelines/__init__.py
flet_timelines/flet_timelines.py
flutter/flet_timelines/CHANGELOG.md
flutter/flet_timelines/LICENSE
flutter/flet_timelines/README.md
flutter/flet_timelines/pubspec.lock
flutter/flet_timelines/pubspec.yaml
flutter/flet_timelines/lib/flet_timelines.dart
flutter/flet_timelines/lib/src/create_control.dart
flutter/flet_timelines/lib/src/flet_timelines.dart
flet_timelines-0.1.2.dist-info/METADATA
flet_timelines-0.1.2.dist-info/WHEEL
flet_timelines-0.1.2.dist-info/top_level.txt
flet_timelines-0.1.2.dist-info/RECORD
