Metadata-Version: 2.2
Name: flet-timelines
Version: 0.1.2
Summary: Timelines control for Flet
Author-email: Flet contributors <you@example.com>
Project-URL: Homepage, https://mydomain.dev
Project-URL: Documentation, https://github.com/MyGithubAccount/flet-timelines
Project-URL: Repository, https://github.com/MyGithubAccount/flet-timelines
Project-URL: Issues, https://github.com/MyGithubAccount/flet-timelines/issues
Requires-Python: >=3.9
Requires-Dist: flet>=0.27.6
